pdm/backend/__init__.py
pdm/backend/_vendor/__init__.py
pdm/backend/_vendor/editables/LICENSE.txt
pdm/backend/_vendor/editables/__init__.py
pdm/backend/_vendor/editables/py.typed
pdm/backend/_vendor/editables/redirector.py
pdm/backend/_vendor/packaging/LICENSE
pdm/backend/_vendor/packaging/LICENSE.APACHE
pdm/backend/_vendor/packaging/LICENSE.BSD
pdm/backend/_vendor/packaging/__init__.py
pdm/backend/_vendor/packaging/_elffile.py
pdm/backend/_vendor/packaging/_manylinux.py
pdm/backend/_vendor/packaging/_musllinux.py
pdm/backend/_vendor/packaging/_parser.py
pdm/backend/_vendor/packaging/_structures.py
pdm/backend/_vendor/packaging/_tokenizer.py
pdm/backend/_vendor/packaging/markers.py
pdm/backend/_vendor/packaging/metadata.py
pdm/backend/_vendor/packaging/py.typed
pdm/backend/_vendor/packaging/requirements.py
pdm/backend/_vendor/packaging/specifiers.py
pdm/backend/_vendor/packaging/tags.py
pdm/backend/_vendor/packaging/utils.py
pdm/backend/_vendor/packaging/version.py
pdm/backend/_vendor/pyproject_metadata/LICENSE
pdm/backend/_vendor/pyproject_metadata/__init__.py
pdm/backend/_vendor/pyproject_metadata/constants.py
pdm/backend/_vendor/pyproject_metadata/errors.py
pdm/backend/_vendor/pyproject_metadata/project_table.py
pdm/backend/_vendor/pyproject_metadata/py.typed
pdm/backend/_vendor/pyproject_metadata/pyproject.py
pdm/backend/_vendor/tomli/LICENSE
pdm/backend/_vendor/tomli/__init__.py
pdm/backend/_vendor/tomli/_parser.py
pdm/backend/_vendor/tomli/_re.py
pdm/backend/_vendor/tomli/_types.py
pdm/backend/_vendor/tomli/py.typed
pdm/backend/_vendor/tomli_w/LICENSE
pdm/backend/_vendor/tomli_w/__init__.py
pdm/backend/_vendor/tomli_w/_writer.py
pdm/backend/_vendor/tomli_w/py.typed
pdm/backend/_vendor/vendor.txt
pdm/backend/base.py
pdm/backend/config.py
pdm/backend/editable.py
pdm/backend/exceptions.py
pdm/backend/hooks/__init__.py
pdm/backend/hooks/base.py
pdm/backend/hooks/setuptools.py
pdm/backend/hooks/version/__init__.py
pdm/backend/hooks/version/scm.py
pdm_backend-2.4.5.dist-info/METADATA
pdm_backend-2.4.5.dist-info/WHEEL
pdm_backend-2.4.5.dist-info/entry_points.txt
pdm_backend-2.4.5.dist-info/licenses/LICENSE
pdm_backend-2.4.5.dist-info/RECORD
