Metadata-Version: 2.1
Name: pdm-backend
Version: 2.4.5
Summary: The build backend used by PDM that supports latest packaging standards
Keywords: packaging,PEP 517,build
Author-Email: Frost Ming <me@frostming.com>
License: MIT
Classifier: Development Status :: 5 - Production/Stable
Classifier: Topic :: Software Development :: Build Tools
Classifier: Programming Language :: Python :: 3
Classifier: Programming Language :: Python :: 3.9
Classifier: Programming Language :: Python :: 3.10
Classifier: Programming Language :: Python :: 3.11
Classifier: Programming Language :: Python :: 3.12
Classifier: Programming Language :: Python :: 3.13
Project-URL: Homepage, https://github.com/pdm-project/pdm-backend
Project-URL: Repository, https://github.com/pdm-project/pdm-backend
Project-URL: Documentation, https://backend.pdm-project.org
Requires-Python: >=3.9
Requires-Dist: importlib-metadata>=3.6; python_version < "3.10"
